br_mongodb_orm/__init__.py
br_mongodb_orm/__version__.py
br_mongodb_orm/config.py
br_mongodb_orm/connection.py
br_mongodb_orm/exceptions.py
br_mongodb_orm/models.py
br_mongodb_orm/types.py
br_mongodb_orm/utils.py
br_mongodb_orm-2.0.2.dist-info/licenses/LICENSE
br_mongodb_orm-2.0.2.dist-info/METADATA
br_mongodb_orm-2.0.2.dist-info/WHEEL
br_mongodb_orm-2.0.2.dist-info/top_level.txt
br_mongodb_orm-2.0.2.dist-info/RECORD
