Metadata-Version: 2.4
Name: br_mongodb_orm
Version: 2.0.2
Summary: Modern async MongoDB ORM for Python with Pydantic integration.
Home-page: https://github.com/asifrahman15/br_mongodb_orm
Author: Aasif Rahman M
Author-email: asifrahman15@gmail.com
License: MIT
Project-URL: Bug Reports, https://github.com/asifrahman15/br_mongodb_orm/issues
Project-URL: Source, https://github.com/asifrahman15/br_mongodb_orm
Project-URL: Documentation, https://github.com/asifrahman15/br_mongodb_orm#readme
Keywords: mongodb orm async motor pydantic database nosql
Classifier: Development Status :: 4 - Beta
Classifier: Intended Audience :: Developers
Classifier: Operating System :: OS Independent
Classifier: Programming Language :: Python :: 3
Classifier: Programming Language :: Python :: 3.8
Classifier: Programming Language :: Python :: 3.9
Classifier: Programming Language :: Python :: 3.10
Classifier: Programming Language :: Python :: 3.11
Classifier: Programming Language :: Python :: 3.12
Classifier: Topic :: Database
Classifier: Topic :: Software Development :: Libraries :: Python Modules
Classifier: Framework :: AsyncIO
Requires-Python: >=3.8
License-File: LICENSE
Requires-Dist: pydantic>=2.8.2
Requires-Dist: motor>=3.5.1
Requires-Dist: pymongo>=4.0.0
Provides-Extra: dev
Requires-Dist: pytest>=7.0.0; extra == "dev"
Requires-Dist: pytest-asyncio>=0.21.0; extra == "dev"
Requires-Dist: pytest-cov>=4.0.0; extra == "dev"
Requires-Dist: black>=23.0.0; extra == "dev"
Requires-Dist: flake8>=5.0.0; extra == "dev"
Requires-Dist: mypy>=1.0.0; extra == "dev"
Provides-Extra: test
Requires-Dist: pytest>=7.0.0; extra == "test"
Requires-Dist: pytest-asyncio>=0.21.0; extra == "test"
Requires-Dist: pytest-cov>=4.0.0; extra == "test"
Dynamic: author
Dynamic: author-email
Dynamic: classifier
Dynamic: description
Dynamic: description-content-type
Dynamic: home-page
Dynamic: keywords
Dynamic: license
Dynamic: license-file
Dynamic: project-url
Dynamic: provides-extra
Dynamic: requires-dist
Dynamic: requires-python
Dynamic: summary
